{
  "feature": "css-standardization",
  "complexity": {
    "level": "L2-SMALL",
    "reasoning": "Incremental approach: 8-12 stories, 2-3 weeks timeline. Creating design token foundation, standardizing 2-3 form components, migrating priority components (FinalCommentsModal, ClassManagementModal). Standard team size, moderate technical complexity. No external integrations or migrations required.",
    "assessedAt": "2025-11-10T00:00:00Z",
    "scope": {
      "stories": "8-12",
      "duration": "2-3 weeks",
      "team": "Small team (Frontend Engineer + Product Owner)",
      "architecture": "Optional - simple refactoring, no major architectural changes"
    }
  },
  "phases": {
    "planning": "COMPLETE",
    "architecture": "NOT_REQUIRED",
    "implementation": "IN_PROGRESS",
    "validation": "NOT_STARTED"
  },
  "completedStories": [
    {
      "id": "US-CSS-001",
      "title": "CSS Architecture Audit & Recommendations",
      "points": 2,
      "completedAt": "2025-11-10",
      "artifacts": ["pdd-workspace/css-standardization/planning/audit-report.md"]
    },
    {
      "id": "US-CSS-002",
      "title": "Design Token System - Core Values",
      "points": 3,
      "completedAt": "2025-11-10",
      "artifacts": [
        "src/theme/tokens.ts",
        "src/theme/__tests__/tokens.test.ts"
      ],
      "testResults": "21 tests passed"
    },
    {
      "id": "US-CSS-003",
      "title": "Standardized Input Component",
      "points": 3,
      "completedAt": "2025-11-10",
      "artifacts": [
        "src/components/common/Input.tsx",
        "src/components/common/Input.css",
        "src/components/common/__tests__/Input.design-tokens.test.tsx"
      ],
      "testResults": "22 tests passed",
      "changes": [
        "Made label prop optional",
        "Updated all styling to use design tokens",
        "Support boolean error prop",
        "Eliminated hardcoded colors #1E3A5F, #F5F8FA",
        "Reduced border width from 2px to 1px (token standard)",
        "Changed background from #F5F8FA to white",
        "Updated label styling: 1.25rem → 0.875rem, navy → gray-700"
      ]
    }
  ],
  "progress": {
    "completedPoints": 8,
    "totalPoints": 18,
    "percentComplete": 44
  },
  "stakeholders": [
    "Development Team",
    "Frontend Engineer",
    "Product Owner"
  ],
  "businessValue": [
    "Faster development through reusable components",
    "Easier maintenance with centralized styling",
    "Consistent user experience",
    "Reduced technical debt",
    "Easier onboarding for new developers"
  ]
}
